odoo/addons/l10n_it_website_portal_fiscalcode/README.rst
odoo/addons/l10n_it_website_portal_fiscalcode/__init__.py
odoo/addons/l10n_it_website_portal_fiscalcode/__manifest__.py
odoo/addons/l10n_it_website_portal_fiscalcode/controllers/__init__.py
odoo/addons/l10n_it_website_portal_fiscalcode/controllers/main.py
odoo/addons/l10n_it_website_portal_fiscalcode/i18n/it.po
odoo/addons/l10n_it_website_portal_fiscalcode/i18n/l10n_it_website_portal_fiscalcode.pot
odoo/addons/l10n_it_website_portal_fiscalcode/readme/DESCRIPTION.rst
odoo/addons/l10n_it_website_portal_fiscalcode/static/description/icon.png
odoo/addons/l10n_it_website_portal_fiscalcode/static/description/index.html
odoo/addons/l10n_it_website_portal_fiscalcode/views/l10n_it_website_portal_fiscalcode_templates.xml
odoo14_addon_l10n_it_website_portal_fiscalcode-14.0.1.0.1.dist-info/METADATA
odoo14_addon_l10n_it_website_portal_fiscalcode-14.0.1.0.1.dist-info/WHEEL
odoo14_addon_l10n_it_website_portal_fiscalcode-14.0.1.0.1.dist-info/top_level.txt
odoo14_addon_l10n_it_website_portal_fiscalcode-14.0.1.0.1.dist-info/RECORD
